pgscatalog/match/__init__.py
pgscatalog/match/cli/__init__.py
pgscatalog/match/cli/_config.py
pgscatalog/match/cli/_write.py
pgscatalog/match/cli/intersect_cli.py
pgscatalog/match/cli/match_cli.py
pgscatalog/match/cli/merge_cli.py
pgscatalog/match/lib/__init__.py
pgscatalog/match/lib/_arrow.py
pgscatalog/match/lib/_config.py
pgscatalog/match/lib/_plinkframe.py
pgscatalog/match/lib/matchresult.py
pgscatalog/match/lib/normalisedscoringfile.py
pgscatalog/match/lib/plinkscorefiles.py
pgscatalog/match/lib/scoringfileframe.py
pgscatalog/match/lib/targetvariants.py
pgscatalog/match/lib/variantframe.py
pgscatalog/match/lib/_match/__init__.py
pgscatalog/match/lib/_match/filter.py
pgscatalog/match/lib/_match/label.py
pgscatalog/match/lib/_match/log.py
pgscatalog/match/lib/_match/match.py
pgscatalog/match/lib/_match/plink.py
pgscatalog/match/lib/_match/preprocess.py
pgscatalog_match-0.4.0.dist-info/licenses/LICENSE
pgscatalog_match-0.4.0.dist-info/METADATA
pgscatalog_match-0.4.0.dist-info/WHEEL
pgscatalog_match-0.4.0.dist-info/entry_points.txt
pgscatalog_match-0.4.0.dist-info/top_level.txt
pgscatalog_match-0.4.0.dist-info/RECORD
