Metadata-Version: 2.4
Name: pgscatalog.match
Version: 0.4.0
Summary: Tools for matching variants in PGS scoring files and target variant information files
Author-email: Benjamin Wingfield <bwingfield@ebi.ac.uk>, Samuel Lambert <sl925@medschl.cam.ac.uk>, Laurent Gil <lg10@sanger.ac.uk>, Florent Yvon <fy279@cam.ac.uk>
License-Expression: Apache-2.0
Classifier: Development Status :: 5 - Production/Stable
Classifier: Environment :: Console
Classifier: Intended Audience :: Science/Research
Classifier: Programming Language :: Python
Classifier: Programming Language :: Python :: 3
Classifier: Programming Language :: Python :: 3.10
Classifier: Programming Language :: Python :: 3.11
Classifier: Programming Language :: Python :: 3.12
Requires-Python: >=3.10
License-File: LICENSE
Requires-Dist: pgscatalog-core>=0.3.3
Requires-Dist: polars==0.20.30
Requires-Dist: pyarrow>=15.0.0
Dynamic: license-file
